record_api/__init__.py
record_api/__main__.py
record_api/apis.py
record_api/combine_apis.py
record_api/core.py
record_api/get_stack.py
record_api/infer_apis.py
record_api/jsonl.py
record_api/jsonl_test.py
record_api/line_counts.py
record_api/pytest_plugin.py
record_api/sample_usage.py
record_api/test.py
record_api/type_analysis.py
record_api/write_api.py
record_api-1.3.2.dist-info/entry_points.txt
record_api-1.3.2.dist-info/LICENSE
record_api-1.3.2.dist-info/WHEEL
record_api-1.3.2.dist-info/METADATA
record_api-1.3.2.dist-info/RECORD
