Metadata-Version: 2.1
Name: record_api
Version: 1.3.2
Summary: Records APIs of Python programs
Home-page: https://github.com/quansight-labs/python_record_api
License: UNKNOWN
Author: Saul Shanabrook
Author-email: s.shanabrook@gmail.com
Classifier: License :: OSI Approved :: MIT License
Requires-Dist: tqdm
Requires-Dist: networkx
Requires-Dist: orjson
Requires-Dist: black
Requires-Dist: pydantic
Requires-Dist: typing_extensions
Requires-Dist: libcst
Requires-Dist: pytest ; extra == "test"
Requires-Dist: numpy ; extra == "test"
Requires-Dist: pandas ; extra == "test"
Provides-Extra: test
